testtools/__init__.py
testtools/_version.py
testtools/assertions.py
testtools/compat.py
testtools/content.py
testtools/content_type.py
testtools/helpers.py
testtools/monkey.py
testtools/run.py
testtools/runtest.py
testtools/tags.py
testtools/testcase.py
testtools/testsuite.py
testtools/matchers/__init__.py
testtools/matchers/_basic.py
testtools/matchers/_const.py
testtools/matchers/_datastructures.py
testtools/matchers/_dict.py
testtools/matchers/_doctest.py
testtools/matchers/_exception.py
testtools/matchers/_filesystem.py
testtools/matchers/_higherorder.py
testtools/matchers/_impl.py
testtools/matchers/_warnings.py
testtools/testresult/__init__.py
testtools/testresult/doubles.py
testtools/testresult/real.py
testtools/tests/__init__.py
testtools/tests/helpers.py
testtools/tests/samplecases.py
testtools/tests/test_assert_that.py
testtools/tests/test_compat.py
testtools/tests/test_content.py
testtools/tests/test_content_type.py
testtools/tests/test_fixturesupport.py
testtools/tests/test_helpers.py
testtools/tests/test_monkey.py
testtools/tests/test_run.py
testtools/tests/test_runtest.py
testtools/tests/test_tags.py
testtools/tests/test_testcase.py
testtools/tests/test_testresult.py
testtools/tests/test_testsuite.py
testtools/tests/test_with_with.py
testtools/tests/matchers/__init__.py
testtools/tests/matchers/helpers.py
testtools/tests/matchers/test_basic.py
testtools/tests/matchers/test_const.py
testtools/tests/matchers/test_datastructures.py
testtools/tests/matchers/test_dict.py
testtools/tests/matchers/test_doctest.py
testtools/tests/matchers/test_exception.py
testtools/tests/matchers/test_filesystem.py
testtools/tests/matchers/test_higherorder.py
testtools/tests/matchers/test_impl.py
testtools/tests/matchers/test_warnings.py
testtools/tests/twistedsupport/__init__.py
testtools/tests/twistedsupport/_helpers.py
testtools/tests/twistedsupport/test_deferred.py
testtools/tests/twistedsupport/test_matchers.py
testtools/tests/twistedsupport/test_runtest.py
testtools-2.8.0.dist-info/METADATA
testtools-2.8.0.dist-info/WHEEL
testtools-2.8.0.dist-info/licenses/LICENSE
testtools-2.8.0.dist-info/RECORD
