Metadata-Version: 2.4
Name: testtools
Version: 2.8.0
Summary: Extensions to the Python standard library unit testing framework
Project-URL: Homepage, https://github.com/testing-cabal/testtools
Author-email: "Jonathan M. Lange" <jml+testtools@mumak.net>
License-File: LICENSE
Classifier: Development Status :: 5 - Production/Stable
Classifier: Intended Audience :: Developers
Classifier: License :: OSI Approved :: MIT License
Classifier: Operating System :: OS Independent
Classifier: Programming Language :: Python
Classifier: Programming Language :: Python :: 3
Classifier: Programming Language :: Python :: 3 :: Only
Classifier: Programming Language :: Python :: 3.10
Classifier: Programming Language :: Python :: 3.11
Classifier: Programming Language :: Python :: 3.12
Classifier: Programming Language :: Python :: 3.13
Classifier: Programming Language :: Python :: 3.14
Classifier: Programming Language :: Python :: Implementation :: CPython
Classifier: Programming Language :: Python :: Implementation :: PyPy
Classifier: Topic :: Software Development :: Libraries
Classifier: Topic :: Software Development :: Libraries :: Python Modules
Classifier: Topic :: Software Development :: Testing
Requires-Python: >=3.10
Provides-Extra: dev
Requires-Dist: ruff==0.14.4; extra == 'dev'
Provides-Extra: test
Requires-Dist: testresources; extra == 'test'
Requires-Dist: testscenarios; extra == 'test'
Provides-Extra: twisted
Requires-Dist: fixtures; extra == 'twisted'
Requires-Dist: twisted; extra == 'twisted'
